deep_autoviml/__init__.py
deep_autoviml/__version__.py
deep_autoviml/deep_autoviml.py
deep_autoviml/data_load/classify_features.py
deep_autoviml/data_load/extract.py
deep_autoviml/modeling/create_model.py
deep_autoviml/modeling/one_cycle.py
deep_autoviml/modeling/predict_model.py
deep_autoviml/modeling/train_custom_model.py
deep_autoviml/modeling/train_image_model.py
deep_autoviml/modeling/train_model.py
deep_autoviml/modeling/train_text_model.py
deep_autoviml/models/basic.py
deep_autoviml/models/cnn1.py
deep_autoviml/models/cnn2.py
deep_autoviml/models/deep_and_wide.py
deep_autoviml/models/dnn.py
deep_autoviml/models/dnn_drop.py
deep_autoviml/models/giant_deep.py
deep_autoviml/models/gru1.py
deep_autoviml/models/lstm1.py
deep_autoviml/models/reg_dnn.py
deep_autoviml/models/rnn1.py
deep_autoviml/models/tf_hub_lookup.py
deep_autoviml/preprocessing/preprocessing.py
deep_autoviml/preprocessing/preprocessing_images.py
deep_autoviml/preprocessing/preprocessing_nlp.py
deep_autoviml/preprocessing/preprocessing_tabular.py
deep_autoviml/preprocessing/preprocessing_text.py
deep_autoviml/utilities/utilities.py
deep_autoviml-0.0.85.dist-info/LICENSE
deep_autoviml-0.0.85.dist-info/METADATA
deep_autoviml-0.0.85.dist-info/WHEEL
deep_autoviml-0.0.85.dist-info/top_level.txt
deep_autoviml-0.0.85.dist-info/RECORD
