Metadata-Version: 2.1
Name: deep_autoviml
Version: 0.0.85
Summary: Automatically Build Deep Learning Models and Pipelines fast!
Home-page: https://github.com/AutoViML/deep_autoviml
Author: Ram Seshadri
License: Apache License 2.0
Classifier: Programming Language :: Python :: 3
Classifier: Operating System :: OS Independent
License-File: LICENSE
Requires-Dist: ipython
Requires-Dist: jupyter
Requires-Dist: tensorflow (<=2.12.1,>=2.8.0)
Requires-Dist: matplotlib (>3.7.4)
Requires-Dist: numpy (>=1.24)
Requires-Dist: pandas (<2.0,>=1.1.3)
Requires-Dist: scikit-learn (<=1.2.2,>=0.24)
Requires-Dist: regex
Requires-Dist: emoji
Requires-Dist: storm-tuner (>=0.0.8)
Requires-Dist: optuna
Requires-Dist: tensorflow-hub (~=0.12.0)
Requires-Dist: tensorflow-text (<=2.12.1,>=2.8.0)
Requires-Dist: tensorboard (<=2.12.3,>=2.8.0)
Requires-Dist: xlrd
